payman/__init__.py
payman/utils.py
payman/core/__init__.py
payman/core/exceptions/__init__.py
payman/core/exceptions/base.py
payman/core/exceptions/http.py
payman/core/gateways/__init__.py
payman/core/gateways/register_gateway.py
payman/core/gateways/wrapper.py
payman/core/http/__init__.py
payman/core/http/client.py
payman/core/http/logger.py
payman/interfaces/__init__.py
payman/interfaces/callback.py
payman/interfaces/gateway_base.py
payman/interfaces/http.py
payman-3.0.3.dist-info/licenses/LICENSE
payman-3.0.3.dist-info/METADATA
payman-3.0.3.dist-info/WHEEL
payman-3.0.3.dist-info/top_level.txt
payman-3.0.3.dist-info/RECORD
