Metadata-Version: 2.4
Name: payman
Version: 3.0.3
Summary: A unified payment gateway SDK for Iranian gateways.
Author-email: AmirAli Irvani <irvaniamirali.dev@gmail.com>
License: GNU GPL v3
Project-URL: homepage, https://github.com/irvaniamirali/payman
Project-URL: repository, https://github.com/irvaniamirali/payman
Project-URL: documentation, https://irvaniamirali.github.io/payman/
License-File: LICENSE
Requires-Dist: pydantic[email]==2.11.7
Requires-Dist: httpx==0.28.1
Requires-Dist: annotated-types==0.7.0
Requires-Dist: anyio==4.9.0
Requires-Dist: certifi==2025.6.15
Requires-Dist: dnspython==2.7.0
Requires-Dist: email-validator==2.2.0
Requires-Dist: h11==0.16.0
Requires-Dist: httpcore==1.0.9
Requires-Dist: idna==3.10
Requires-Dist: iniconfig==2.1.0
Requires-Dist: packaging==25.0
Requires-Dist: pluggy==1.6.0
Requires-Dist: pygments==2.19.2
Requires-Dist: sniffio==1.3.1
Requires-Dist: typing-inspection==0.4.1
Requires-Dist: typing-extensions==4.14.0
Provides-Extra: zibal
Requires-Dist: payman-zibal>=1.0.1; extra == "zibal"
Dynamic: license-file
